python_radix/__init__.py
python_radix/python_radix.py
python_radix_ng-0.3.1.dist-info/LICENSE
python_radix_ng-0.3.1.dist-info/METADATA
python_radix_ng-0.3.1.dist-info/WHEEL
python_radix_ng-0.3.1.dist-info/top_level.txt
python_radix_ng-0.3.1.dist-info/RECORD
