Metadata-Version: 2.1
Name: python-radix-ng
Version: 0.3.1
Summary: A tool for converting numbers from one base to another, TheTechRobo edition
Home-page: https://github.com/TheTechRobo/python-radix
Author: valbub, yury-khrustalev, mulkieran, TheTechRobo
License: MIT
Keywords: radix numbers bases number systems base36
Platform: Any
Classifier: Development Status :: 5 - Production/Stable
Classifier: Intended Audience :: Developers
Classifier: License :: OSI Approved :: MIT License
Classifier: Programming Language :: Python :: 3
Classifier: Programming Language :: Python :: 3.4
